{
  "UserAgent": "MobileHub/1.0",
  "Version": "1.0",
  "CredentialsProvider": {
    "CognitoIdentity": {
      "Default": {
        "PoolId": "ap-northeast-2:0d6ef9c8-574f-456b-83b1-68f3d916d460",
        "Region": "ap-northeast-2"
      }
    }
  },
  "IdentityManager": {
    "Default": {}
  },
  "S3TransferUtility": {
    "Default": {
      "Bucket": "zumundev-userfiles-mobilehub-724946108",
      "Region": "ap-northeast-2"
    }
  },
  "PinpointAnalytics": {
    "Default": {
      "AppId": "de0b0b095ea845d98378cc19e859ed55",
      "Region": "us-east-1"
    }
  },
  "PinpointTargeting": {
    "Default": {
      "Region": "us-east-1"
    }
  },
  "UserFileManager": {
    "Default": {
      "Bucket": "zumundev-userfiles-mobilehub-724946108",
      "Region": "ap-northeast-2"
    }
  }
}